CHANGES.txt
CONTRIBUTORS.txt
MANIFEST.in
README.txt
setup.py
docs/LICENSE.GPL
docs/LICENSE.txt
src/raptus/__init__.py
src/raptus.article.supersized.egg-info/PKG-INFO
src/raptus.article.supersized.egg-info/SOURCES.txt
src/raptus.article.supersized.egg-info/dependency_links.txt
src/raptus.article.supersized.egg-info/entry_points.txt
src/raptus.article.supersized.egg-info/namespace_packages.txt
src/raptus.article.supersized.egg-info/not-zip-safe
src/raptus.article.supersized.egg-info/requires.txt
src/raptus.article.supersized.egg-info/top_level.txt
src/raptus/article/__init__.py
src/raptus/article/supersized/__init__.py
src/raptus/article/supersized/configure.zcml
src/raptus/article/supersized/setuphandlers.py
src/raptus/article/supersized/browser/__init__.py
src/raptus/article/supersized/browser/configure.zcml
src/raptus/article/supersized/browser/supersized.gif
src/raptus/article/supersized/browser/supersized.pt
src/raptus/article/supersized/browser/supersized.py
src/raptus/article/supersized/browser/supersized_teaser.gif
src/raptus/article/supersized/i18n/raptus.article-de.mo
src/raptus/article/supersized/i18n/raptus.article-de.po
src/raptus/article/supersized/i18n/raptus.article.pot
src/raptus/article/supersized/profiles/default/cssregistry.xml
src/raptus/article/supersized/profiles/default/metadata.xml
src/raptus/article/supersized/profiles/default/propertiestool.xml
src/raptus/article/supersized/profiles/default/raptus.article.supersized_install.txt
src/raptus/article/supersized/profiles/default/skins.xml
src/raptus/article/supersized/profiles/default/viewlets.xml
src/raptus/article/supersized/skins/raptus_article_supersized/raptus.article.supersized.css.dtml