Metadata-Version: 1.0
Name: raptus.article.supersized
Version: 1.0a1
Summary: UNKNOWN
Home-page: http://svn.plone.org/svn/collective/raptus.article/raptus.article.supersized
Author: Raptus AG
Author-email: dev@raptus.com
License: gpl
Platform: UNKNOWN
Classifier: Programming Language :: Python
